<?xml version="1.0" encoding="utf-8" ?>
<Triggers>
  <Trigger>
    <HeartRateLower>0</HeartRateLower>
    <HeartRateUpper>48</HeartRateUpper>
    <ShowMode>ShowMode00</ShowMode>
  </Trigger>
  <Trigger>
    <HeartRateLower>49</HeartRateLower>
    <HeartRateUpper>50</HeartRateUpper>
    <ShowMode>ShowMode01</ShowMode>
  </Trigger>
  <Trigger>
    <HeartRateLower>51</HeartRateLower>
    <HeartRateUpper>52</HeartRateUpper>
    <ShowMode>ShowMode01</ShowMode>
  </Trigger>
  <Trigger>
    <HeartRateLower>53</HeartRateLower>
    <HeartRateUpper>54</HeartRateUpper>
    <ShowMode>ShowMode02</ShowMode>
  </Trigger>
  <Trigger>
    <HeartRateLower>55</HeartRateLower>
    <HeartRateUpper>56</HeartRateUpper>
    <ShowMode>ShowMode02</ShowMode>
  </Trigger>
  <Trigger>
    <HeartRateLower>57</HeartRateLower>
    <HeartRateUpper>58</HeartRateUpper>
    <ShowMode>MultiMode01</ShowMode>
  </Trigger>
  <Trigger>
    <HeartRateLower>59</HeartRateLower>
    <HeartRateUpper>60</HeartRateUpper>
    <ShowMode>MultiMode01</ShowMode>
  </Trigger>
  <Trigger>
    <HeartRateLower>61</HeartRateLower>
    <HeartRateUpper>62</HeartRateUpper>
    <ShowMode>MultiMode01</ShowMode>
  </Trigger>
  <Trigger>
    <HeartRateLower>63</HeartRateLower>
    <HeartRateUpper>64</HeartRateUpper>
    <ShowMode>MultiMode01</ShowMode>
  </Trigger>
  <Trigger>
    <HeartRateLower>65</HeartRateLower>
    <HeartRateUpper>66</HeartRateUpper>
    <ShowMode>ShowMode09</ShowMode>
  </Trigger>
  <Trigger>
    <HeartRateLower>67</HeartRateLower>
    <HeartRateUpper>68</HeartRateUpper>
    <ShowMode>ShowMode10</ShowMode>
  </Trigger>
  <Trigger>
    <HeartRateLower>69</HeartRateLower>
    <HeartRateUpper>70</HeartRateUpper>
    <ShowMode>ShowMode11</ShowMode>
  </Trigger>
  <Trigger>
    <HeartRateLower>71</HeartRateLower>
    <HeartRateUpper>72</HeartRateUpper>
    <ShowMode>ShowMode12</ShowMode>
    <!--<ShowMode>MultiMode01</ShowMode>-->
  </Trigger>
  <Trigger>
    <HeartRateLower>73</HeartRateLower>
    <HeartRateUpper>74</HeartRateUpper>
    <ShowMode>ShowMode13</ShowMode>
  </Trigger>
  <Trigger>
    <HeartRateLower>75</HeartRateLower>
    <HeartRateUpper>76</HeartRateUpper>
    <ShowMode>ShowMode14</ShowMode>
  </Trigger>
  <Trigger>
    <HeartRateLower>77</HeartRateLower>
    <HeartRateUpper>78</HeartRateUpper>
    <ShowMode>ShowMode15</ShowMode>
  </Trigger>
  <Trigger>
    <HeartRateLower>79</HeartRateLower>
    <HeartRateUpper>80</HeartRateUpper>
    <ShowMode>ShowMode16</ShowMode>
  </Trigger>
  <Trigger>
    <HeartRateLower>81</HeartRateLower>
    <HeartRateUpper>82</HeartRateUpper>
    <ShowMode>ShowMode17</ShowMode>
  </Trigger>
  <Trigger>
    <HeartRateLower>83</HeartRateLower>
    <HeartRateUpper>84</HeartRateUpper>
    <ShowMode>ShowMode18</ShowMode>
  </Trigger>
  <Trigger>
    <HeartRateLower>85</HeartRateLower>
    <HeartRateUpper>86</HeartRateUpper>
    <ShowMode>ShowMode19</ShowMode>
  </Trigger>
  <Trigger>
    <HeartRateLower>87</HeartRateLower>
    <HeartRateUpper>88</HeartRateUpper>
    <ShowMode>ShowMode20</ShowMode>
  </Trigger>
  <Trigger>
    <HeartRateLower>89</HeartRateLower>
    <HeartRateUpper>90</HeartRateUpper>
    <ShowMode>ShowMode21</ShowMode>
  </Trigger>
  <Trigger>
    <HeartRateLower>91</HeartRateLower>
    <HeartRateUpper>92</HeartRateUpper>
    <ShowMode>ShowMode22</ShowMode>
  </Trigger>
  <Trigger>
    <HeartRateLower>93</HeartRateLower>
    <HeartRateUpper>94</HeartRateUpper>
    <ShowMode>ShowMode23</ShowMode>
  </Trigger>
  <Trigger>
    <HeartRateLower>95</HeartRateLower>
    <HeartRateUpper>96</HeartRateUpper>
    <ShowMode>ShowMode24</ShowMode>
  </Trigger>
  <Trigger>
    <HeartRateLower>97</HeartRateLower>
    <HeartRateUpper>98</HeartRateUpper>
    <ShowMode>ShowMode25</ShowMode>
  </Trigger>
  <Trigger>
    <HeartRateLower>99</HeartRateLower>
    <HeartRateUpper>100</HeartRateUpper>
    <ShowMode>ShowMode26</ShowMode>
  </Trigger>
  <Trigger>
    <HeartRateLower>101</HeartRateLower>
    <HeartRateUpper>102</HeartRateUpper>
    <ShowMode>ShowMode27</ShowMode>
  </Trigger>
  <Trigger>
    <HeartRateLower>103</HeartRateLower>
    <HeartRateUpper>104</HeartRateUpper>
    <ShowMode>ShowMode28</ShowMode>
  </Trigger>
  <Trigger>
    <HeartRateLower>105</HeartRateLower>
    <HeartRateUpper>106</HeartRateUpper>
    <ShowMode>ShowMode29</ShowMode>
  </Trigger>
  <Trigger>
    <HeartRateLower>107</HeartRateLower>
    <HeartRateUpper>108</HeartRateUpper>
    <ShowMode>ShowMode30</ShowMode>
  </Trigger>
  <Trigger>
    <HeartRateLower>109</HeartRateLower>
    <HeartRateUpper>110</HeartRateUpper>
    <ShowMode>ShowMode31</ShowMode>
  </Trigger>
  <Trigger>
    <HeartRateLower>111</HeartRateLower>
    <HeartRateUpper>112</HeartRateUpper>
    <ShowMode>ShowMode32</ShowMode>
  </Trigger>
  <Trigger>
    <HeartRateLower>113</HeartRateLower>
    <HeartRateUpper>114</HeartRateUpper>
    <ShowMode>ShowMode33</ShowMode>
  </Trigger>
  <Trigger>
    <HeartRateLower>115</HeartRateLower>
    <HeartRateUpper>116</HeartRateUpper>
    <ShowMode>ShowMode34</ShowMode>
  </Trigger>
  <Trigger>
    <HeartRateLower>117</HeartRateLower>
    <HeartRateUpper>118</HeartRateUpper>
    <ShowMode>ShowMode35</ShowMode>
  </Trigger>
  <Trigger>
    <HeartRateLower>119</HeartRateLower>
    <HeartRateUpper>120</HeartRateUpper>
    <ShowMode>ShowMode36</ShowMode>
  </Trigger>
  <Trigger>
    <HeartRateLower>121</HeartRateLower>
    <HeartRateUpper>122</HeartRateUpper>
    <ShowMode>ShowMode37</ShowMode>
  </Trigger>
  <Trigger>
    <HeartRateLower>123</HeartRateLower>
    <HeartRateUpper>124</HeartRateUpper>
    <ShowMode>ShowMode38</ShowMode>
  </Trigger>
  <Trigger>
    <HeartRateLower>125</HeartRateLower>
    <HeartRateUpper>126</HeartRateUpper>
    <ShowMode>ShowMode39</ShowMode>
  </Trigger>
  <Trigger>
    <HeartRateLower>127</HeartRateLower>
    <HeartRateUpper>128</HeartRateUpper>
    <ShowMode>ShowMode40</ShowMode>
  </Trigger>
</Triggers>