<?xml version="1.0" encoding="utf-8" ?>
<Triggers>
  <Trigger>
    <HeartRateLower>0</HeartRateLower>
    <HeartRateUpper>55</HeartRateUpper>
    <ShowMode>ShowMode01</ShowMode>
  </Trigger>
  <Trigger>
    <HeartRateLower>56</HeartRateLower>
    <HeartRateUpper>60</HeartRateUpper>
    <ShowMode>ShowMode02</ShowMode>
  </Trigger>
  <Trigger>
    <HeartRateLower>61</HeartRateLower>
    <HeartRateUpper>65</HeartRateUpper>
    <ShowMode>ShowMode03</ShowMode>
  </Trigger>
  <Trigger>
    <HeartRateLower>66</HeartRateLower>
    <HeartRateUpper>500</HeartRateUpper>
    <ShowMode>ShowMode04</ShowMode>
  </Trigger>
</Triggers>